async_bash_mcp/__init__.py
async_bash_mcp-0.1.6.dist-info/WHEEL
async_bash_mcp-0.1.6.dist-info/entry_points.txt
async_bash_mcp-0.1.6.dist-info/METADATA
async_bash_mcp-0.1.6.dist-info/RECORD
