Metadata-Version: 2.3
Name: async-bash-mcp
Version: 0.1.6
Summary: A robust subprocess execution MCP
Author: Huw Percival
Author-email: Huw Percival <huw.percival@gmail.com>
Requires-Dist: mcp>=1.12.3
Requires-Dist: platformdirs>=4.3.8
Requires-Dist: pytest>=7.0.0 ; extra == 'dev'
Requires-Dist: pytest-asyncio>=0.21.0 ; extra == 'dev'
Requires-Dist: ruff ; extra == 'dev'
Requires-Python: >=3.13
Provides-Extra: dev
